vllm_df11/__init__.py
vllm_df11/dfloat11_decode_v2.cpython-313-x86_64-linux-gnu.so
vllm_df11/loader.py
vllm_df11/plugin.py
vllm_df11/quantization.py
vllm_df11.libs/libcudart-c3a75b33.so.12.8.90
vllm_df11-0.0.1.dist-info/METADATA
vllm_df11-0.0.1.dist-info/WHEEL
vllm_df11-0.0.1.dist-info/entry_points.txt
vllm_df11-0.0.1.dist-info/top_level.txt
vllm_df11-0.0.1.dist-info/RECORD
vllm_df11-0.0.1.dist-info/licenses/LICENSE
