Metadata-Version: 2.4
Name: vllm-df11
Version: 0.0.1
Summary: Dfloat11 plugin for vLLM
Author-email: Mohsen Hariri <mohsen.hariri@case.edu>, Tianyi Zhang <tz21@rice.edu>
License-Expression: Apache-2.0
Classifier: Programming Language :: Python :: 3.9
Classifier: Programming Language :: Python :: 3.11
Classifier: Programming Language :: Python :: 3.12
Classifier: Programming Language :: Python :: 3.13
Classifier: Intended Audience :: Developers
Classifier: Intended Audience :: Information Technology
Classifier: Intended Audience :: Science/Research
Classifier: Topic :: Scientific/Engineering :: Artificial Intelligence
Classifier: Topic :: Scientific/Engineering :: Information Analysis
Requires-Python: <3.14,>=3.9
License-File: LICENSE
Dynamic: license-file
